hwtGraph/__init__.py
hwtGraph/elk/__init__.py
hwtGraph/elk/containers/__init__.py
hwtGraph/elk/containers/constants.py
hwtGraph/elk/containers/idStore.py
hwtGraph/elk/containers/lEdge.py
hwtGraph/elk/containers/lNode.py
hwtGraph/elk/containers/lPort.py
hwtGraph/elk/fromHwt/__init__.py
hwtGraph/elk/fromHwt/convertor.py
hwtGraph/elk/fromHwt/defauts.py
hwtGraph/elk/fromHwt/extractSplits.py
hwtGraph/elk/fromHwt/flattenTrees.py
hwtGraph/elk/fromHwt/mergeSplitsOnInterfaces.py
hwtGraph/elk/fromHwt/netCtx.py
hwtGraph/elk/fromHwt/netlistPreprocessors.py
hwtGraph/elk/fromHwt/propagatePresets.py
hwtGraph/elk/fromHwt/reduceUselessAssignments.py
hwtGraph/elk/fromHwt/resolveSharedConnections.py
hwtGraph/elk/fromHwt/sortStatementPorts.py
hwtGraph/elk/fromHwt/statementRenderer.py
hwtGraph/elk/fromHwt/statementRendererUtils.py
hwtGraph/elk/fromHwt/utils.py
hwtGraph-2.1.dist-info/LICENSE
hwtGraph-2.1.dist-info/METADATA
hwtGraph-2.1.dist-info/WHEEL
hwtGraph-2.1.dist-info/top_level.txt
hwtGraph-2.1.dist-info/zip-safe
hwtGraph-2.1.dist-info/RECORD
