Metadata-Version: 2.1
Name: hwtGraph
Version: 2.1
Summary: Library for conversion of HWT hardware representation to graph formats for visualization purposes
Home-page: https://github.com/Nic30/hwtGraph
Author: Michal Orsak
Author-email: Nic30original@gmail.com
License: MIT
Platform: UNKNOWN
Classifier: Development Status :: 4 - Beta
Classifier: Intended Audience :: Developers
Classifier: License :: OSI Approved :: MIT License
Classifier: Operating System :: OS Independent
Classifier: Programming Language :: Python :: 3 :: Only
Classifier: Programming Language :: Python :: 3
Classifier: Programming Language :: Python :: 3.5
Classifier: Programming Language :: Python :: 3.6
Classifier: Programming Language :: Python :: 3.7
Classifier: Topic :: Scientific/Engineering :: Electronic Design Automation (EDA)
Classifier: Topic :: System :: Hardware
Classifier: Topic :: Utilities
License-File: LICENSE
Requires-Dist: hwt (>=3.8)
